Spruce_project-0.1.3-py2.7-nspkg.pth
spruce/project/vcs.py
spruce/project/__init__.py
spruce/project/scripts/doc_gen_rest.py
spruce/project/scripts/__init__.py
Spruce_project-0.1.3.dist-info/top_level.txt
Spruce_project-0.1.3.dist-info/RECORD
Spruce_project-0.1.3.dist-info/pydist.json
Spruce_project-0.1.3.dist-info/WHEEL
Spruce_project-0.1.3.dist-info/namespace_packages.txt
Spruce_project-0.1.3.dist-info/METADATA
Spruce_project-0.1.3.dist-info/entry_points.txt
Spruce_project-0.1.3.dist-info/DESCRIPTION.rst
Spruce_project-0.1.3.data/scripts/project-doc-gen-rest
