Metadata-Version: 2.0
Name: Spruce-project
Version: 0.1.3
Summary: Project inspection, management, and administration
Home-page: UNKNOWN
Author: Ivan D Vasin
Author-email: nisavid@gmail.com
License: GNU LESSER GENERAL PUBLIC LICENSE
Requires-Dist: spruce-introspect
Requires-Dist: spruce-pprint
